prfiesta/__init__.py
prfiesta/__main__.py
prfiesta/analysis/__init__.py
prfiesta/analysis/plot.py
prfiesta/analysis/view.py
prfiesta/collectors/__init__.py
prfiesta/collectors/github.py
prfiesta/environment.py
prfiesta/output.py
prfiesta/spinner.py
prfiesta-0.14.0.dist-info/LICENSE
prfiesta-0.14.0.dist-info/METADATA
prfiesta-0.14.0.dist-info/WHEEL
prfiesta-0.14.0.dist-info/entry_points.txt
prfiesta-0.14.0.dist-info/RECORD
