Metadata-Version: 2.3
Name: prfiesta
Version: 0.14.0
Summary: Collect and Analyze Individual Contributor Pull Requests
Home-page: https://pypi.org/project/prfiesta/
License: MIT
Keywords: pull-request,pull-request-review,performance-review
Author: kiran94
Requires-Python: >=3.9,<4.0
Classifier: Intended Audience :: Developers
Classifier: License :: OSI Approved :: MIT License
Classifier: Operating System :: OS Independent
Classifier: Programming Language :: Python :: 3
Classifier: Programming Language :: Python :: 3.9
Classifier: Programming Language :: Python :: 3.10
Classifier: Programming Language :: Python :: 3.11
Classifier: Programming Language :: Python :: 3.12
Classifier: Programming Language :: Python :: 3.13
Classifier: Topic :: Software Development
Classifier: Topic :: Software Development :: Version Control :: Git
Classifier: Topic :: Utilities
Requires-Dist: click (>=8.1.3,<9.0.0)
Requires-Dist: cloup (>=2.1.0,<3.0.0)
Requires-Dist: duckdb (>=1.1.3,<2.0.0)
Requires-Dist: matplotlib (>=3.7.1,<4.0.0)
Requires-Dist: natural (>=0.2.0,<0.3.0)
Requires-Dist: numpy (<2)
Requires-Dist: pandas (>=2.0.1,<3.0.0)
Requires-Dist: pyarrow (>=18.1.0,<19.0.0)
Requires-Dist: pygithub (>=1.58.1,<2.0.0)
Requires-Dist: rich (>=13.3.5,<14.0.0)
Requires-Dist: seaborn (>=0.12.2,<0.13.0)
Requires-Dist: urllib3 (<2)
Project-URL: Documentation, https://github.com/kiran94/prfiesta/blob/main/README.md
Project-URL: Repository, https://github.com/kiran94/prfiesta
